LICENSE
default_setting_overrides.json
nbgrader_config.py
setup.py
bin/methnum
methnum/__init__.py
methnum.egg-info/PKG-INFO
methnum.egg-info/SOURCES.txt
methnum.egg-info/dependency_links.txt
methnum.egg-info/requires.txt
methnum.egg-info/top_level.txt