Metadata-Version: 2.1
Name: methnum
Version: 3.0.dev0
Summary: Required software for using the MethNum course material
Home-page: https://gitlab.dsi.universite-paris-saclay.fr/MethNum
Author: Jérémy Neveu, Nicolas M. Thiéry et al.
Author-email: jeremy.neveu@universite-paris-saclay.fr
License: CC
Classifier: Development Status :: 4 - Beta
Classifier: Intended Audience :: Information Technology
Classifier: Topic :: Scientific/Engineering
Classifier: Programming Language :: Python
License-File: LICENSE
Requires-Dist: travo[jupyter]>=1.0
Requires-Dist: nbgrader>=0.9.1
Requires-Dist: jupytext
